{
  "resourceType": "CodeSystem",
  "status": "active",
  "content": "complete",
  "name": "NZResidency",
  "id": "nz-residency",
  "title": "NZ Residency status",
  "description": "NZ Residency status",
  "url": "https://standards.digital.health.nz/ns/nz-residency-code",
  "concept": [
    {
      "code": "yes",
      "display": "Permanent Resident",
      "definition": "Use this status if the person holds a residence class visa"
    },
    {
      "code": "no",
      "display": "Not a Permanent Resident",
      "definition": "Use this status for a person who is a NZ Citizen or does not hold a residence class visa"
    },
    {
      "code": "unknown",
      "display": "Unknown",
      "definition": "use this status if the residency status of the person cannot be determined or is unknown"
    }
  ],
  "caseSensitive": true,
  "version": "1.1.0",
  "experimental": false,
  "count": 3
}
