{
  "resourceType": "Practitioner",
  "id": "practitioner-scope-of-practice",
  "name": [
    {
      "family": "Doe",
      "given": [
        "John"
      ],
      "text": "John Doe"
    }
  ],
  "birthDate": "1998-01-01",
  "gender": "male",
  "qualification": [
    {
      "code": {
        "coding": [
          {
            "code": "BS",
            "system": "http://terminology.hl7.org/CodeSystem/v2-0360"
          }
        ]
      },
      "extension": [
        {
          "url": "http://hl7.org.nz/fhir/StructureDefinition/scope-of-practice",
          "extension": [
            {
              "url": "code",
              "valueCodeableConcept": {
                "coding": [
                  {
                    "code": "CHIR",
                    "system": "https://standards.digital.health.nz/ns/practitioner-scope-of-practice-code",
                    "display": "Chiropractor"
                  }
                ]
              }
            },
            {
              "url": "period",
              "valuePeriod": {
                "start": "2020-01-01",
                "end": "2020-12-31"
              }
            }
          ]
        }
      ]
    }
  ]
}
